translation.cpython-310-x86_64-linux-gnu.so
ribosomesimulator.cpython-310-x86_64-linux-gnu.so
elongation_simulators-1.0.5.data/scripts/simulationbuilder.py
elongation_simulators-1.0.5.data/scripts/basepairingeditor.py
elongation_simulators-1.0.5.dist-info/RECORD
elongation_simulators-1.0.5.dist-info/LICENSE
elongation_simulators-1.0.5.dist-info/METADATA
elongation_simulators-1.0.5.dist-info/WHEEL
elongation_simulators-1.0.5.dist-info/top_level.txt
concentrations/Saccharomyces_cerevisiae.csv
concentrations/concentrations_generator.py
concentrations/basepairingeditor.py
concentrations/__init__.py
concentrations/default_basepairing.json
elongation/simulationbuilder.py
elongation/__init__.py
elongation/utils.py
