Metadata-Version: 2.1
Name: elongation-simulators
Version: 1.0.5
Summary: High-performance Ribosome simulator and elongation simulator for eukaryotic organism
Home-page: https://github.com/fheday/elongation_simulator/
Author: Fabio Hedayioglu
Author-email: fheday@gmail.com
Maintainer: Fabio Hedayioglu
Maintainer-email: fheday@gmail.com
License: MIT License
Keywords: elongation translation
Platform: UNKNOWN
Classifier: Development Status :: 3 - Alpha
Classifier: Intended Audience :: Science/Research
Classifier: License :: OSI Approved :: MIT License
Classifier: Programming Language :: C++
Classifier: Programming Language :: Python :: 3 :: Only
Classifier: Programming Language :: Python :: 3
Classifier: Programming Language :: Python :: 3.8
Classifier: Programming Language :: Python :: 3.9
Classifier: Programming Language :: Python :: 3.10
Classifier: Programming Language :: Python :: 3.11
Classifier: Programming Language :: Python :: 3.12
Classifier: Programming Language :: Python
License-File: LICENSE
Requires-Dist: pybind11
Requires-Dist: pytest
Requires-Dist: numpy
Requires-Dist: pyqt5
